{
  "id": "HAI",
  "name": "Haiti",
  "emoji": "🇭🇹",
  "group": "C",
  "coach": "",
  "formation": "4-4-2",
  "stats": {
    "matchesPlayed": 1,
    "wins": 0,
    "draws": 0,
    "losses": 1,
    "goalsFor": 0,
    "goalsAgainst": 1,
    "points": 0,
    "totalXG": 0.7,
    "xGAgainst": 0.91,
    "avgPossession": 52,
    "avgPassCompletion": 88,
    "avgTotalPasses": 431,
    "avgCompletedPasses": 378,
    "totalShots": 15,
    "shotsOnTarget": 2,
    "shotAccuracy": 13,
    "corners": 4,
    "crossesAttempted": 19,
    "crossesCompleted": 3,
    "avgPressures": 185,
    "avgDirectPressures": 35,
    "avgBallRecoverySeconds": 14.86,
    "avgPressureDuration_s": 1.52,
    "avgTotalDistance_km": 113.7,
    "avgZone4Distance_km": 5.9,
    "cleanSheets": 0,
    "topSpeedKmh": 34.2,
    "topSpeedPlayer": "Jean-Ricner BELLEGARDE",
    "gkSavePercent": 50,
    "gkAttemptsOnGoalFaced": 9
  },
  "matches": [
    {
      "matchId": "2026-06-13-HAI-SCO",
      "opponent": "SCO",
      "score": "0-1",
      "result": "L",
      "xG": 0.7
    }
  ],
  "squad": [
    { "number": 1,  "name": "Johny PLACIDE",        "position": "GK" },
    { "number": 2,  "name": "Carlens ARCUS",         "position": "DF" },
    { "number": 3,  "name": "Keeto THERMONCY",       "position": "DF" },
    { "number": 4,  "name": "Ricardo ADE",           "position": "DF" },
    { "number": 5,  "name": "Hannes DELCROIX",       "position": "DF" },
    { "number": 6,  "name": "Carl SAINTE",           "position": "MF" },
    { "number": 7,  "name": "Derrick ETIENNE",       "position": "MF" },
    { "number": 8,  "name": "Martin EXPERIENCE",     "position": "DF" },
    { "number": 9,  "name": "Duckens NAZON",         "position": "FW" },
    { "number": 10, "name": "Jean-Ricner BELLEGARDE","position": "MF" },
    { "number": 11, "name": "Louicius DEEDSON",      "position": "MF" },
    { "number": 12, "name": "Alexandre PIERRE",      "position": "GK" },
    { "number": 13, "name": "Markhus LACROIX",       "position": "MF" },
    { "number": 14, "name": "Garven METUSALA",       "position": "MF" },
    { "number": 15, "name": "Ruben PROVIDENCE",      "position": "MF" },
    { "number": 16, "name": "Lenny JOSEPH",          "position": "MF" },
    { "number": 17, "name": "Danley JEAN JACQUES",   "position": "DF" },
    { "number": 18, "name": "Wilson ISIDOR",         "position": "FW" },
    { "number": 19, "name": "Yassin FORTUNE",        "position": "MF" },
    { "number": 20, "name": "Frantzdy PIERROT",      "position": "FW" },
    { "number": 21, "name": "Josue CASIMIR",         "position": "MF" },
    { "number": 22, "name": "Jean-Kevin DUVERNE",    "position": "DF" },
    { "number": 23, "name": "Josue DUVERGER",        "position": "MF" },
    { "number": 24, "name": "Wilguens PAUGAIN",      "position": "MF" },
    { "number": 25, "name": "Dominique SIMON",       "position": "MF" },
    { "number": 26, "name": "Woodensky PIERRE",      "position": "MF" }
  ]
}
