{
  "id": "QAT",
  "name": "Qatar",
  "emoji": "🇶🇦",
  "group": "B",
  "coach": "Marquez Lopez",
  "formation": "4-2-3-1",
  "stats": {
    "matchesPlayed": 2,
    "wins": 0,
    "draws": 1,
    "losses": 1,
    "goalsFor": 1,
    "goalsAgainst": 7,
    "points": 1,
    "totalXG": 0.72,
    "xGAgainst": 7.04,
    "avgPossession": 26.8,
    "avgPassCompletion": 69,
    "avgTotalPasses": 228,
    "avgCompletedPasses": 160,
    "totalShots": 8,
    "shotsOnTarget": 3,
    "shotAccuracy": 38,
    "crossesAttempted": 7,
    "crossesCompleted": 2,
    "completedLineBreaks": 81,
    "avgBallProgressions": 10,
    "avgReceptionsInFinalThird": 26,
    "avgPressures": 284,
    "avgDirectPressures": 43,
    "avgBallRecoverySeconds": 19.72,
    "avgPressureDuration_s": 1.47,
    "avgForcedTurnovers": 30,
    "avgPossessionRegains": 114,
    "avgTackles": 15,
    "avgBlocks": 18,
    "avgInterceptions": 2,
    "avgAerialDuels": 5,
    "avgTotalDistance_km": 100.0,
    "avgZone4Distance_km": 4.3,
    "cleanSheets": 0,
    "topSpeedKmh": 33.2,
    "topSpeedPlayer": "AKRAM AFIF",
    "gkSavePercent": 64,
    "gkAttemptsOnGoalFaced": 63
  },
  "matches": [
    {
      "matchId": "2026-06-13-QAT-SUI",
      "opponent": "SUI",
      "score": "1-1",
      "result": "D",
      "xG": 0.52
    },
    {
      "matchId": "2026-06-18-CAN-QAT",
      "opponent": "CAN",
      "score": "0-6",
      "result": "L",
      "xG": 0.2
    }
  ],
  "squad": [
    { "number": 1,  "name": "MAHMOUD ABUNADA",    "position": "GK" },
    { "number": 2,  "name": "PEDRO MIGUEL",        "position": "DF" },
    { "number": 3,  "name": "LUCAS MENDES",        "position": "DF" },
    { "number": 4,  "name": "ISSA LAYE",            "position": "DF" },
    { "number": 5,  "name": "JASSEM GABER",         "position": "DF" },
    { "number": 6,  "name": "ABDULAZIZ HATEM",      "position": "MF" },
    { "number": 7,  "name": "AHMED ALAAELDIN",      "position": "FW" },
    { "number": 8,  "name": "EDMILSON JUNIOR",      "position": "FW" },
    { "number": 9,  "name": "MOHAMMED MUNTARI",     "position": "FW" },
    { "number": 10, "name": "HASSAN ALHAYDOS",      "position": "FW" },
    { "number": 11, "name": "AKRAM AFIF",           "position": "FW" },
    { "number": 12, "name": "KARIM BOUDIAF",        "position": "MF" },
    { "number": 13, "name": "AYOUB ALOUI",          "position": "DF" },
    { "number": 14, "name": "HOMAM AHMED",          "position": "DF" },
    { "number": 15, "name": "YUSUF ABDURISAG",      "position": "FW" },
    { "number": 16, "name": "BOUALEM KHOUKHI",      "position": "DF" },
    { "number": 17, "name": "AHMED ALGANEHI",       "position": "MF" },
    { "number": 18, "name": "SULTAN ALBRAKE",       "position": "DF" },
    { "number": 19, "name": "ALMOEZ ALI",           "position": "FW" },
    { "number": 20, "name": "AHMED FATHY",          "position": "MF" },
    { "number": 21, "name": "SALAH ZAKARIA",        "position": "GK" },
    { "number": 22, "name": "MESHAAL BARSHAM",      "position": "GK" },
    { "number": 23, "name": "ASSIM MADIBO",         "position": "MF" },
    { "number": 24, "name": "TAHSIN MOHAMMED",      "position": "FW" },
    { "number": 25, "name": "ALHASHMI ALHUSSEIN",   "position": "DF" },
    { "number": 26, "name": "MOHAMED MANAI",        "position": "FW" }
  ]
}
